<manifest alg="2" build="2018.1.0.386" opt="true" iceEnabled="true" iceMarkupVersion="2" iceEnabledOptions="link,responsive,cachebuster,textStyling" exportTarget="other" domain="rbkserapis.com" resolutions="1x,2x" timestamp="1540815998879">
  <folder name="css">
    <file name="site_global.css" crc="373709799"/>
    <file name="master_arabic--master.css" crc="372201965" ref="apply-here-arabic:about-arabic:home-arabic:faq-arabic"/>
    <file name="master_english-master.css" crc="68332539" ref="about:index:f.a.q:apply-here"/>
    <file name="apply-here-arabic.css" crc="433653853" ref="apply-here-arabic"/>
    <file name="about.css" crc="3953110540" ref="about"/>
    <file name="iefonts_about.css" crc="126544615" ref="about"/>
    <file name="index.css" crc="32136578" ref="index"/>
    <file name="iefonts_index.css" crc="4106989620" ref="index"/>
    <file name="about-arabic.css" crc="444375766" ref="about-arabic"/>
    <file name="home-arabic.css" crc="32870028" ref="home-arabic"/>
    <file name="iefonts_home-arabic.css" crc="125849251" ref="home-arabic"/>
    <file name="f_a_q.css" crc="195348265" ref="f.a.q"/>
    <file name="iefonts_f_a_q.css" crc="4257025791" ref="f.a.q"/>
    <file name="faq-arabic.css" crc="4190784104" ref="faq-arabic"/>
    <file name="apply-here.css" crc="135039400" ref="apply-here"/>
    <file name="iefonts_apply-here.css" crc="126544615" ref="apply-here"/>
  </folder>
  <folder name="scripts">
    <file name="jquery-1.8.3.min.js" crc="209076791" ref="phone>index:phone>volunteer:phone>faq:phone>about:phone>about-arabic:index:home-arabic:f.a.q:faq-arabic:apply-here:apply-here-arabic:about:about-arabic"/>
    <file name="museutils.js" crc="340535759" ref="phone>index:phone>volunteer:phone>faq:phone>about:phone>about-arabic:index:home-arabic:f.a.q:faq-arabic:apply-here:apply-here-arabic:about:about-arabic"/>
    <file name="whatinput.js" crc="86476730" ref="phone>index:phone>volunteer:phone>faq:phone>about:phone>about-arabic:index:home-arabic:f.a.q:faq-arabic:apply-here:apply-here-arabic:about:about-arabic"/>
    <file name="museconfig.js" crc="310584261" ref="phone>index:phone>volunteer:phone>faq:phone>about:phone>about-arabic:index:home-arabic:f.a.q:faq-arabic:apply-here:apply-here-arabic:about:about-arabic"/>
    <file name="jquery.watch.js" crc="51536988" ref="phone>index:phone>volunteer:phone>faq:phone>about:phone>about-arabic:index:home-arabic:f.a.q:faq-arabic:apply-here:apply-here-arabic:about:about-arabic"/>
    <file name="jquery.musepolyfill.bgsize.js" crc="4260645839" ref="phone>index:phone>volunteer:index:home-arabic"/>
    <file name="webpro.js" crc="4059564322" ref="phone>index:phone>volunteer:phone>faq:index:home-arabic:f.a.q:faq-arabic:apply-here:about"/>
    <file name="musewpdisclosure.js" crc="3883500470" ref="phone>index:phone>faq:index:f.a.q:faq-arabic:apply-here:about"/>
    <file name="musewpslideshow.js" crc="3862962738" ref="phone>index:phone>volunteer:phone>faq:about"/>
    <file name="jquery.museoverlay.js" crc="4147669564" ref="phone>index:phone>volunteer:phone>faq:about"/>
    <file name="touchswipe.js" crc="4075097462" ref="phone>index:phone>volunteer:phone>faq:about"/>
    <file name="form_check.php" crc="4020933626" ref="phone>index"/>
    <file name="form_throttle.php" crc="4259590256" ref="phone>index"/>
    <file name="form_process.php" crc="37464564" ref="phone>index"/>
    <file name="form-u17234.php" crc="3876376343" ref="phone>index"/>
    <file name="require.js" crc="7928878" ref="phone>index:phone>volunteer:phone>faq:phone>about:phone>about-arabic:index:home-arabic:f.a.q:faq-arabic:apply-here:apply-here-arabic:about:about-arabic"/>
    <file name="form-u19973.php" crc="4166221035" ref="phone>volunteer"/>
    <file name="jquery.musemenu.js" crc="510910590" ref="index:home-arabic:f.a.q:faq-arabic:apply-here:apply-here-arabic:about:about-arabic"/>
    <file name="form-u21992.php" crc="437562046" ref="index"/>
    <file name="html5shiv.js" crc="4241844378" ref="index:home-arabic:f.a.q:faq-arabic:apply-here:apply-here-arabic:about:about-arabic"/>
    <file name="form-u22098.php" crc="3836049967" ref="home-arabic"/>
  </folder>
  <folder name="images">
    <file name="serapis@2x.png" crc="380264861" seo="true" ref="phone>index:phone>volunteer:phone>faq:phone>about:index:home-arabic:f.a.q:faq-arabic:apply-here:apply-here-arabic:about:about-arabic">
      <caption webpage="home-arabic" alt=""/>
      <caption webpage="volunteer" alt=""/>
      <caption webpage="apply-here" alt=""/>
      <caption webpage="about" alt=""/>
      <caption webpage="about" alt=""/>
      <caption webpage="faq" alt=""/>
      <caption webpage="index" alt=""/>
      <caption webpage="index" alt=""/>
      <caption webpage="about-arabic" alt=""/>
      <caption webpage="f.a.q" alt=""/>
      <caption webpage="faq-arabic" alt=""/>
      <caption webpage="apply-here-arabic" alt=""/>
    </file>
    <file name="logobootcamp@2x.png" crc="35377135" seo="true" ref="phone>index:phone>volunteer:phone>faq:phone>about:index:home-arabic:f.a.q:faq-arabic:apply-here:apply-here-arabic:about:about-arabic">
      <caption webpage="home-arabic" alt=""/>
      <caption webpage="volunteer" alt=""/>
      <caption webpage="apply-here" alt=""/>
      <caption webpage="about" alt=""/>
      <caption webpage="about" alt=""/>
      <caption webpage="faq" alt=""/>
      <caption webpage="index" alt=""/>
      <caption webpage="index" alt=""/>
      <caption webpage="about-arabic" alt=""/>
      <caption webpage="f.a.q" alt=""/>
      <caption webpage="faq-arabic" alt=""/>
      <caption webpage="apply-here-arabic" alt=""/>
    </file>
    <file name="pointer.png" crc="3760686964" seo="true" ref="phone>index:phone>volunteer:phone>faq">
      <caption webpage="index" alt=""/>
      <caption webpage="index" alt=""/>
      <caption webpage="index" alt=""/>
      <caption webpage="index" alt=""/>
      <caption webpage="index" alt=""/>
      <caption webpage="index" alt=""/>
      <caption webpage="index" alt=""/>
      <caption webpage="volunteer" alt=""/>
      <caption webpage="volunteer" alt=""/>
      <caption webpage="volunteer" alt=""/>
      <caption webpage="volunteer" alt=""/>
      <caption webpage="faq" alt=""/>
      <caption webpage="faq" alt=""/>
      <caption webpage="faq" alt=""/>
      <caption webpage="faq" alt=""/>
    </file>
    <file name="pointer_2x.png" crc="3760686964" seo="true" ref="phone>index:phone>volunteer:phone>faq">
      <caption webpage="index" alt=""/>
      <caption webpage="index" alt=""/>
      <caption webpage="index" alt=""/>
      <caption webpage="index" alt=""/>
      <caption webpage="index" alt=""/>
      <caption webpage="index" alt=""/>
      <caption webpage="index" alt=""/>
      <caption webpage="volunteer" alt=""/>
      <caption webpage="volunteer" alt=""/>
      <caption webpage="volunteer" alt=""/>
      <caption webpage="volunteer" alt=""/>
      <caption webpage="faq" alt=""/>
      <caption webpage="faq" alt=""/>
      <caption webpage="faq" alt=""/>
      <caption webpage="faq" alt=""/>
    </file>
    <file name="znewlogo.png" crc="3921563352" ref="phone>index:index:home-arabic">
      <caption webpage="index" alt=""/>
    </file>
    <file name="znewlogo_2x.png" crc="3812761507" ref="phone>index:index:home-arabic">
      <caption webpage="index" alt=""/>
    </file>
    <file name="relo-logo.jpg" crc="129936040" ref="phone>index:index:home-arabic">
      <caption webpage="index" alt=""/>
    </file>
    <file name="800px_colourbox9513134-u15351-fr.png" crc="4165034389" ref="phone>index"/>
    <file name="800px_colourbox9513134-u15351-fr_2x.png" crc="4083737575" ref="phone>index"/>
    <file name="u15217-4.png" crc="528648980" ref="phone>index"/>
    <file name="u15217-4_2x.png" crc="3948311959" ref="phone>index"/>
    <file name="menu_icon_04_white_3line-crop-u19633.png" crc="4158053167" seo="true" ref="phone>index">
      <caption webpage="index" alt=""/>
    </file>
    <file name="u15415-10.png" crc="4289240495" ref="phone>index"/>
    <file name="u15415-10_2x.png" crc="4138547467" ref="phone>index"/>
    <file name="u15412-4.png" crc="514825964" ref="phone>index"/>
    <file name="u15412-4_2x.png" crc="139318540" ref="phone>index"/>
    <file name="800px_colourbox9513134.jpg" crc="245692946" ref="phone>index">
      <caption webpage="index" alt=""/>
    </file>
    <file name="800px_colourbox9513134_2x.jpg" crc="427539485" ref="phone>index">
      <caption webpage="index" alt=""/>
    </file>
    <file name="checkboxunchecked.jpg" crc="495023700" ref="phone>volunteer">
      <caption webpage="volunteer" alt=""/>
    </file>
    <file name="checkboxunchecked_2x.jpg" crc="4041065271" ref="phone>volunteer">
      <caption webpage="volunteer" alt=""/>
    </file>
    <file name="checkboxuncheckedrollover.jpg" crc="4076496830" ref="phone>volunteer">
      <caption webpage="volunteer" alt=""/>
    </file>
    <file name="checkboxuncheckedrollover_2x.jpg" crc="421393327" ref="phone>volunteer">
      <caption webpage="volunteer" alt=""/>
    </file>
    <file name="checkboxuncheckedmousedown.jpg" crc="361678653" ref="phone>volunteer">
      <caption webpage="volunteer" alt=""/>
    </file>
    <file name="checkboxuncheckedmousedown_2x.jpg" crc="119826174" ref="phone>volunteer">
      <caption webpage="volunteer" alt=""/>
    </file>
    <file name="checkboxchecked.jpg" crc="477278992" ref="phone>volunteer">
      <caption webpage="volunteer" alt=""/>
    </file>
    <file name="checkboxchecked_2x.jpg" crc="8340162" ref="phone>volunteer">
      <caption webpage="volunteer" alt=""/>
    </file>
    <file name="checkboxcheckedrollover.jpg" crc="435737969" ref="phone>volunteer">
      <caption webpage="volunteer" alt=""/>
    </file>
    <file name="checkboxcheckedrollover_2x.jpg" crc="461578639" ref="phone>volunteer">
      <caption webpage="volunteer" alt=""/>
    </file>
    <file name="checkboxcheckedmousedown.jpg" crc="4004261994" ref="phone>volunteer">
      <caption webpage="volunteer" alt=""/>
    </file>
    <file name="checkboxcheckedmousedown_2x.jpg" crc="3782867047" ref="phone>volunteer">
      <caption webpage="volunteer" alt=""/>
    </file>
    <file name="menu_icon_04_white_3line-crop-u19894.png" crc="4158053167" seo="true" ref="phone>volunteer">
      <caption webpage="volunteer" alt=""/>
    </file>
    <file name="menu_icon_04_white_3line-crop-u20558.png" crc="4158053167" seo="true" ref="phone>faq">
      <caption webpage="faq" alt=""/>
    </file>
    <file name="ppppink.png" crc="95871282" ref="index:home-arabic">
      <caption webpage="index" alt=""/>
    </file>
    <file name="u5326-4.png" crc="143515710" ref="index"/>
    <file name="u5326-4_2x.png" crc="4065811961" ref="index"/>
    <file name="group 171@2x.png" crc="405677236" seo="true" ref="index:home-arabic:f.a.q:faq-arabic:apply-here:apply-here-arabic:about:about-arabic">
      <caption webpage="home-arabic" alt=""/>
      <caption webpage="apply-here" alt=""/>
      <caption webpage="about" alt=""/>
      <caption webpage="index" alt=""/>
      <caption webpage="about-arabic" alt=""/>
      <caption webpage="f.a.q" alt=""/>
      <caption webpage="faq-arabic" alt=""/>
      <caption webpage="apply-here-arabic" alt=""/>
    </file>
    <file name="curves@2x.png" crc="3955068999" ref="index:home-arabic">
      <caption webpage="index" alt=""/>
      <caption webpage="home-arabic" alt=""/>
    </file>
    <file name="u5329-4.png" crc="3920741575" ref="index"/>
    <file name="u5329-4_2x.png" crc="526736966" ref="index"/>
    <file name="mdcard.png" crc="321711723" seo="true" ref="index:home-arabic">
      <caption webpage="index" alt=""/>
      <caption webpage="index" alt=""/>
      <caption webpage="index" alt=""/>
      <caption webpage="index" alt=""/>
      <caption webpage="index" alt=""/>
      <caption webpage="index" alt=""/>
      <caption webpage="index" alt=""/>
      <caption webpage="index" alt=""/>
      <caption webpage="index" alt=""/>
      <caption webpage="index" alt=""/>
      <caption webpage="index" alt=""/>
      <caption webpage="home-arabic" alt=""/>
      <caption webpage="home-arabic" alt=""/>
      <caption webpage="home-arabic" alt=""/>
      <caption webpage="home-arabic" alt=""/>
      <caption webpage="home-arabic" alt=""/>
      <caption webpage="home-arabic" alt=""/>
      <caption webpage="home-arabic" alt=""/>
      <caption webpage="home-arabic" alt=""/>
      <caption webpage="home-arabic" alt=""/>
      <caption webpage="home-arabic" alt=""/>
      <caption webpage="home-arabic" alt=""/>
    </file>
    <file name="lololololo@2x.png" crc="133327900" ref="index:home-arabic">
      <caption webpage="index" alt=""/>
    </file>
    <file name="picture13635489459274@2x.png" crc="3818114851" ref="index:home-arabic">
      <caption webpage="index" alt=""/>
    </file>
    <file name="garageband-icon@2x.png" crc="4266267853" ref="index:home-arabic">
      <caption webpage="index" alt=""/>
    </file>
    <file name="pasted image 312x52.png" crc="88858916" seo="true" ref="index:home-arabic">
      <caption webpage="index" alt=""/>
      <caption webpage="index" alt=""/>
      <caption webpage="index" alt=""/>
      <caption webpage="index" alt=""/>
      <caption webpage="index" alt=""/>
      <caption webpage="index" alt=""/>
      <caption webpage="index" alt=""/>
      <caption webpage="index" alt=""/>
      <caption webpage="index" alt=""/>
      <caption webpage="home-arabic" alt=""/>
      <caption webpage="home-arabic" alt=""/>
      <caption webpage="home-arabic" alt=""/>
      <caption webpage="home-arabic" alt=""/>
      <caption webpage="home-arabic" alt=""/>
      <caption webpage="home-arabic" alt=""/>
      <caption webpage="home-arabic" alt=""/>
      <caption webpage="home-arabic" alt=""/>
      <caption webpage="home-arabic" alt=""/>
    </file>
    <file name="u6363-4.png" crc="192076489" ref="index"/>
    <file name="u6363-4_2x.png" crc="4001618213" ref="index"/>
    <file name="u6362-4.png" crc="4258746181" ref="index"/>
    <file name="u6362-4_2x.png" crc="3789133574" ref="index"/>
    <file name="u6364-4.png" crc="477482676" ref="index"/>
    <file name="u6364-4_2x.png" crc="4162947458" ref="index"/>
    <file name="microsoft-powerpoint-mac-icon@2x.png" crc="4288572186" ref="index:home-arabic">
      <caption webpage="index" alt=""/>
    </file>
    <file name="microsoft-excel-mac-icon@2x.png" crc="458500032" ref="index:home-arabic">
      <caption webpage="index" alt=""/>
    </file>
    <file name="microsoft-word-mac-icon@2x.png" crc="432036660" ref="index:home-arabic">
      <caption webpage="index" alt=""/>
    </file>
    <file name="u6366-4.png" crc="4276856557" ref="index"/>
    <file name="u6366-4_2x.png" crc="208099134" ref="index"/>
    <file name="u6365-4.png" crc="372201769" ref="index"/>
    <file name="u6365-4_2x.png" crc="4225219832" ref="index"/>
    <file name="u6367-4.png" crc="3964076304" ref="index"/>
    <file name="u6367-4_2x.png" crc="472256390" ref="index"/>
    <file name="adobe-photoshop-icon@2x.png" crc="280468681" ref="index:home-arabic">
      <caption webpage="index" alt=""/>
    </file>
    <file name="adobe-illustrator-icon@2x.png" crc="3843973237" ref="index:home-arabic">
      <caption webpage="index" alt=""/>
    </file>
    <file name="adobe-premiere-icon@2x.png" crc="4186056801" ref="index:home-arabic">
      <caption webpage="index" alt=""/>
    </file>
    <file name="u6369-4.png" crc="4263618860" ref="index"/>
    <file name="u6369-4_2x.png" crc="27262641" ref="index"/>
    <file name="u6368-4.png" crc="107956239" ref="index"/>
    <file name="u6368-4_2x.png" crc="387846165" ref="index"/>
    <file name="u6370-4.png" crc="282116922" ref="index"/>
    <file name="u6370-4_2x.png" crc="4025136697" ref="index"/>
    <file name="u5824-4.png" crc="3787453390" ref="home-arabic"/>
    <file name="u5824-4_2x.png" crc="187388474" ref="home-arabic"/>
    <file name="u5825-4.png" crc="4278209966" ref="home-arabic"/>
    <file name="u5825-4_2x.png" crc="3786306339" ref="home-arabic"/>
    <file name="u19277-5.png" crc="3899655834" ref="home-arabic"/>
    <file name="u19277-5_2x.png" crc="4086562893" ref="home-arabic"/>
    <file name="u5827-4.png" crc="3866827635" ref="home-arabic"/>
    <file name="u5827-4_2x.png" crc="3990605838" ref="home-arabic"/>
    <file name="u6288-4.png" crc="192076489" ref="home-arabic"/>
    <file name="u6288-4_2x.png" crc="4001618213" ref="home-arabic"/>
    <file name="u6285-4.png" crc="4258746181" ref="home-arabic"/>
    <file name="u6285-4_2x.png" crc="3789133574" ref="home-arabic"/>
    <file name="u6291-4.png" crc="477482676" ref="home-arabic"/>
    <file name="u6291-4_2x.png" crc="4162947458" ref="home-arabic"/>
    <file name="u6295-4.png" crc="4276856557" ref="home-arabic"/>
    <file name="u6295-4_2x.png" crc="208099134" ref="home-arabic"/>
    <file name="u6294-4.png" crc="372201769" ref="home-arabic"/>
    <file name="u6294-4_2x.png" crc="4225219832" ref="home-arabic"/>
    <file name="u6296-4.png" crc="3964076304" ref="home-arabic"/>
    <file name="u6296-4_2x.png" crc="472256390" ref="home-arabic"/>
    <file name="u6304-4.png" crc="4263618860" ref="home-arabic"/>
    <file name="u6304-4_2x.png" crc="27262641" ref="home-arabic"/>
    <file name="u6303-4.png" crc="107956239" ref="home-arabic"/>
    <file name="u6303-4_2x.png" crc="387846165" ref="home-arabic"/>
    <file name="u6305-4.png" crc="282116922" ref="home-arabic"/>
    <file name="u6305-4_2x.png" crc="4025136697" ref="home-arabic"/>
    <file name="u11930-5.png" crc="14662758" ref="home-arabic"/>
    <file name="u11930-5_2x.png" crc="478314481" ref="home-arabic"/>
    <file name="u7005-4.png" crc="3963643285" ref="f.a.q"/>
    <file name="u7005-4_2x.png" crc="522888830" ref="f.a.q"/>
    <file name="u8298-5.png" crc="232201706" ref="faq-arabic"/>
    <file name="u8298-5_2x.png" crc="3964105759" ref="faq-arabic"/>
    <file name="u8498-4.png" crc="4143498939" ref="apply-here"/>
    <file name="u8498-4_2x.png" crc="334222018" ref="apply-here"/>
    <file name="u9461-4.png" crc="4005247410" ref="apply-here-arabic"/>
    <file name="u9461-4_2x.png" crc="500176488" ref="apply-here-arabic"/>
    <file name="u9805-4.png" crc="272729444" ref="about"/>
    <file name="u9805-4_2x.png" crc="3834123099" ref="about"/>
    <file name="u22271-4.png" crc="3842777563" ref="about"/>
    <file name="u22271-4_2x.png" crc="3796197144" ref="about"/>
    <file name="u11245-5.png" crc="454967353" ref="about-arabic"/>
    <file name="u11245-5_2x.png" crc="307451544" ref="about-arabic"/>
  </folder>
  <folder name="phone">
    <folder name="css">
      <file name="master_english-master.css" crc="17735640" ref="phone>about:phone>index:phone>volunteer:phone>faq"/>
      <file name="about.css" crc="193264702" ref="phone>about"/>
      <file name="index.css" crc="3797446787" ref="phone>index"/>
      <file name="iefonts_index.css" crc="4072611030" ref="phone>index"/>
      <file name="volunteer.css" crc="161210590" ref="phone>volunteer"/>
      <file name="iefonts_volunteer.css" crc="484801896" ref="phone>volunteer"/>
      <file name="about-arabic.css" crc="279237556" ref="phone>about-arabic"/>
      <file name="faq.css" crc="156826155" ref="phone>faq"/>
      <file name="iefonts_faq.css" crc="268084696" ref="phone>faq"/>
    </folder>
    <file name="index.html" crc="4181643311" seo="true" mt="1540815774600" redirect="true"/>
    <file name="volunteer.html" crc="3912514906" seo="true" mt="1540815774600" redirect="true"/>
    <file name="faq.html" crc="526040416" seo="true" mt="1540815774600" redirect="true"/>
    <file name="about.html" crc="474998296" seo="true" mt="1540815774600" redirect="true"/>
    <file name="about-arabic.html" crc="4004266154" seo="true" mt="1540296759593" redirect="false"/>
  </folder>
  <file name="index.html" crc="498856171" seo="true" mt="1540815931986" redirect="true"/>
  <file name="home-arabic.html" crc="4063366393" seo="true" mt="1540815812572" redirect="true"/>
  <file name="f.a.q.html" crc="471826570" seo="true" mt="1540690600769" redirect="true"/>
  <file name="faq-arabic.html" crc="279869468" seo="true" mt="1540815787843" redirect="true"/>
  <file name="apply-here.html" crc="4101988670" seo="true" mt="1540690600769" redirect="true"/>
  <file name="apply-here-arabic.html" crc="267593899" seo="true" mt="1540815787843" redirect="true"/>
  <file name="about.html" crc="4265065967" seo="true" mt="1540690600769" redirect="true"/>
  <file name="about-arabic.html" crc="3802952880" seo="true" mt="1540815787843" redirect="true"/>
</manifest>